discount_properties_pkg/__init__.py
discount_properties_pkg/discount_properties.py
hima_discount-0.0.2.dist-info/LICENCE.txt
hima_discount-0.0.2.dist-info/METADATA
hima_discount-0.0.2.dist-info/WHEEL
hima_discount-0.0.2.dist-info/top_level.txt
hima_discount-0.0.2.dist-info/RECORD
